{
    "key": "group_5e87733f57bf0",
    "title": "Choix de la catégorie des articles à afficher dans cette page",
    "fields": [
        {
            "key": "field_5e87735942a89",
            "label": "Choisir une categorie",
            "name": "choisir_une_categorie",
            "type": "taxonomy",
            "instructions": "",
            "required": 0,
            "conditional_logic": 0,
            "wrapper": {
                "width": "",
                "class": "",
                "id": ""
            },
            "taxonomy": "category",
            "field_type": "multi_select",
            "allow_null": 0,
            "add_term": 0,
            "save_terms": 0,
            "load_terms": 0,
            "return_format": "id",
            "wpml_cf_preferences": 1,
            "multiple": 0
        }
    ],
    "location": [
        [
            {
                "param": "post_type",
                "operator": "==",
                "value": "page"
            }
        ]
    ],
    "menu_order": 0,
    "position": "side",
    "style": "default",
    "label_placement": "top",
    "instruction_placement": "label",
    "hide_on_screen": "",
    "active": 1,
    "description": "",
    "modified": 1585935300
}